{ "head": {
    "vars": [ "IEName" , "IAName" , "IE" ]
  } ,
  "results": {
    "bindings": [
      { 
        "IEName": { "type": "literal" , "value": "CS Req 1" } ,
        "IAName": { "type": "literal" , "value": "Cybersecurity Requirements Document" } ,
        "IE": { "type": "uri" , "value": "http://uaontologies.com/dTEMP_Rover/MR_Requirements#CS_Req1" }
      } ,
      { 
        "IEName": { "type": "literal" , "value": "CS Req 2" } ,
        "IAName": { "type": "literal" , "value": "Cybersecurity Requirements Document" } ,
        "IE": { "type": "uri" , "value": "http://uaontologies.com/dTEMP_Rover/MR_Requirements#CS_Req2" }
      } ,
      { 
        "IEName": { "type": "literal" , "value": "Comms Test Result" } ,
        "IAName": { "type": "literal" , "value": "Rover Development Test Incident Report" } ,
        "IE": { "type": "uri" , "value": "http://uaontologies.com/dTEMP_Rover/MR_TestResults#CommsTest_Result" }
      } ,
      { 
        "IEName": { "type": "literal" , "value": "Debris Threat Description" } ,
        "IAName": { "type": "literal" , "value": "Threat Description Document" } ,
        "IE": { "type": "uri" , "value": "http://uaontologies.com/dTEMP_Rover/MR_TestProgram#DebrisThreatDescription" }
      } ,
      { 
        "IEName": { "type": "literal" , "value": "KPP 1" } ,
        "IAName": { "type": "literal" , "value": "Key Performance Parameters and Key System Attributes Document" } ,
        "IE": { "type": "uri" , "value": "http://uaontologies.com/dTEMP_Rover/MR_Requirements#KPP_1" }
      } ,
      { 
        "IEName": { "type": "literal" , "value": "KPP 2" } ,
        "IAName": { "type": "literal" , "value": "Key Performance Parameters and Key System Attributes Document" } ,
        "IE": { "type": "uri" , "value": "http://uaontologies.com/dTEMP_Rover/MR_Requirements#KPP_2" }
      } ,
      { 
        "IEName": { "type": "literal" , "value": "KSA 1" } ,
        "IAName": { "type": "literal" , "value": "Key Performance Parameters and Key System Attributes Document" } ,
        "IE": { "type": "uri" , "value": "http://uaontologies.com/dTEMP_Rover/MR_Requirements#KSA_1" }
      } ,
      { 
        "IEName": { "type": "literal" , "value": "KSA 2" } ,
        "IAName": { "type": "literal" , "value": "Key Performance Parameters and Key System Attributes Document" } ,
        "IE": { "type": "uri" , "value": "http://uaontologies.com/dTEMP_Rover/MR_Requirements#KSA_2" }
      } ,
      { 
        "IEName": { "type": "literal" , "value": "Low Power Test Data" } ,
        "IAName": { "type": "literal" , "value": "Payload Test Data Report" } ,
        "IE": { "type": "uri" , "value": "http://uaontologies.com/dTEMP_Rover/MR_TestResults#LowPowerTestData" }
      } ,
      { 
        "IEName": { "type": "literal" , "value": "Material Developer Spec" } ,
        "IAName": { "type": "literal" , "value": "Operational Test Readiness Report" } ,
        "IE": { "type": "uri" , "value": "http://uaontologies.com/dTEMP_Rover/MR_TestProgram#MATDEV_OTRS" }
      } ,
      { 
        "IEName": { "type": "literal" , "value": "Payload Test Data" } ,
        "IAName": { "type": "literal" , "value": "Payload Test Data Report" } ,
        "IE": { "type": "uri" , "value": "http://uaontologies.com/dTEMP_Rover/MR_TestResults#PayloadTestData" }
      } ,
      { 
        "IEName": { "type": "literal" , "value": "RCA 1" } ,
        "IAName": { "type": "literal" , "value": "Rover Document TEMP" } ,
        "IE": { "type": "uri" , "value": "http://uaontologies.com/dTEMP_Rover/MR_TestProgram#RecommendedCorrectiveAction1" }
      } ,
      { 
        "IEName": { "type": "literal" , "value": "RCA 2" } ,
        "IAName": { "type": "literal" , "value": "Rover Document TEMP" } ,
        "IE": { "type": "uri" , "value": "http://uaontologies.com/dTEMP_Rover/MR_TestProgram#RecommendedCorrectiveAction2" }
      } ,
      { 
        "IEName": { "type": "literal" , "value": "Radiation Threat Description" } ,
        "IAName": { "type": "literal" , "value": "Threat Description Document" } ,
        "IE": { "type": "uri" , "value": "http://uaontologies.com/dTEMP_Rover/MR_TestProgram#RadiationThreatDescription" }
      } ,
      { 
        "IEName": { "type": "literal" , "value": "Rover IDSK" } ,
        "IAName": { "type": "literal" , "value": "Rover Document TEMP" } ,
        "IE": { "type": "uri" , "value": "http://uaontologies.com/dTEMP_Rover/MR_TestProgram#Rover_IDSK" }
      } ,
      { 
        "IEName": { "type": "literal" , "value": "Rover TEMP" } ,
        "IAName": { "type": "literal" , "value": "Rover Document TEMP" } ,
        "IE": { "type": "uri" , "value": "http://uaontologies.com/dTEMP_Rover/MR_TestProgram#Rover_TEMP" }
      } ,
      { 
        "IEName": { "type": "literal" , "value": "Rover WIPT Overview" } ,
        "IAName": { "type": "literal" , "value": "Rover WIPT Charter" } ,
        "IE": { "type": "uri" , "value": "http://uaontologies.com/dTEMP_Rover/MR_Organization#Rover_WIPT_Info" }
      } ,
      { 
        "IEName": { "type": "literal" , "value": "SE Procedure" } ,
        "IAName": { "type": "literal" , "value": "Systems Engineering Procedures Document" } ,
        "IE": { "type": "uri" , "value": "http://uaontologies.com/dTEMP_Rover/MR_Organization#SEProcedure" }
      } ,
      { 
        "IEName": { "type": "literal" , "value": "TAT Atmospheric Dust" } ,
        "IAName": { "type": "literal" , "value": "Target Acquisition Test Procedure" } ,
        "IE": { "type": "uri" , "value": "http://uaontologies.com/dTEMP_Rover/MR_Tests#TargetAcquisitionTest_AtmosphericDust_Planned" }
      } ,
      { 
        "IEName": { "type": "literal" , "value": "TAT Lighting" } ,
        "IAName": { "type": "literal" , "value": "Target Acquisition Test Procedure" } ,
        "IE": { "type": "uri" , "value": "http://uaontologies.com/dTEMP_Rover/MR_Tests#TargetAcquisitionTest_Lighting_Planned" }
      } ,
      { 
        "IEName": { "type": "literal" , "value": "TAT Procedure" } ,
        "IAName": { "type": "literal" , "value": "Target Acquisition Test Procedure" } ,
        "IE": { "type": "uri" , "value": "http://uaontologies.com/dTEMP_Rover/MR_Tests#TargetAcquisitionTest_Procedure" }
      } ,
      { 
        "IEName": { "type": "literal" , "value": "TEMP Review Procedure" } ,
        "IAName": { "type": "literal" , "value": "TEMP Review Procedure" } ,
        "IE": { "type": "uri" , "value": "http://uaontologies.com/dTEMP_Rover/MR_TestProgram#TEMPReviewProcedure" }
      } ,
      { 
        "IEName": { "type": "literal" , "value": "Target Acquisition Result" } ,
        "IAName": { "type": "literal" , "value": "Rover Operational Test Incident Report" } ,
        "IE": { "type": "uri" , "value": "http://uaontologies.com/dTEMP_Rover/MR_TestResults#TargetAcquisitionTest_Result" }
      } ,
      { 
        "IEName": { "type": "literal" , "value": "Tech Risk Assessment 1" } ,
        "IAName": { "type": "literal" , "value": "Rover Document TEMP" } ,
        "IE": { "type": "uri" , "value": "http://uaontologies.com/dTEMP_Rover/MR_Tests#TechRiskAssessment1" }
      } ,
      { 
        "IEName": { "type": "literal" , "value": "Torque Test Data" } ,
        "IAName": { "type": "literal" , "value": "Mobility Torque Test Data" } ,
        "IE": { "type": "uri" , "value": "http://uaontologies.com/dTEMP_Rover/MR_TestResults#TorqueTestData" }
      }
    ]
  }
}
